DLDummyGen/DLDummyGen-non-oop.py
DLDummyGen/DLDummyGen.py
DLDummyGen/__init__.py
DLDummyGen-0.0.2.dist-info/LICENSE
DLDummyGen-0.0.2.dist-info/METADATA
DLDummyGen-0.0.2.dist-info/WHEEL
DLDummyGen-0.0.2.dist-info/top_level.txt
DLDummyGen-0.0.2.dist-info/RECORD
