Metadata-Version: 2.1
Name: DLDummyGen
Version: 0.0.2
Summary: Deep-Learning Dummy File Generator by csv File
Home-page: https://github.com/ryuvsken
Author: ryuvsken
Author-email: ryuvskendev@gmail.com
License: UNKNOWN
Platform: UNKNOWN
Classifier: License :: OSI Approved :: MIT License
Requires-Dist: numpy
Requires-Dist: pandas
Requires-Dist: faker
